PISOShiftReg.vhd
--------------------------------------------------------------------------------
-- PISO-Schieberegister als mögliche Grundlage für die Implementierung der RS232-
-- Schnittstelle im Hardwarepraktikum
--------------------------------------------------------------------------------
library ieee;
use ieee.std_logic_1164.all;

entity PISOShiftReg is
    generic (
        WIDTH    : integer := 8
    );
    port (
        CLK      : in  std_logic;
        CLK_EN   : in  std_logic;
        LOAD     : in  std_logic;
        D_IN     : in  std_logic_vector(WIDTH-1 downto 0);
        D_OUT    : out std_logic;
        LAST_BIT : out std_logic
    );
end entity PISOShiftReg;

architecture behavioral of PISOShiftReg is
    -- Internes Schieberegister: enthaelt das geladene Datum und wird taktweise
    -- nach rechts geschoben, sodass die Bits vom LSB zum MSB seriell ausgegeben
    -- werden.
    signal shift_reg    : std_logic_vector(WIDTH-1 downto 0) := (others => '0');

    -- Marker-Register als One-Hot-Zeiger: zu Beginn steht das gesetzte Bit an
    -- der MSB-Position und wandert mit jedem Shift mit. Erreicht es Position 0,
    -- liegt das MSB des Datums am Ausgang an.
    signal marker       : std_logic_vector(WIDTH-1 downto 0) := (others => '0');

    -- Sticky-Flag: bleibt nach dem Ausgeben des MSB '1', bis ein neues Datum
    -- geladen wird.
    signal last_bit_reg : std_logic := '0';
begin
    D_OUT    <= shift_reg(0);
    LAST_BIT <= last_bit_reg;

    SHIFT_PROC : process(CLK) is
        variable new_marker : std_logic_vector(WIDTH-1 downto 0);
    begin
        if rising_edge(CLK) then
            if CLK_EN = '1' then
                if LOAD = '1' then
                    -- Datum uebernehmen, Marker auf MSB-Position setzen,
                    -- LAST_BIT zuruecksetzen.
                    shift_reg                  <= D_IN;
                    marker                     <= (others => '0');
                    marker(WIDTH-1)            <= '1';
                    last_bit_reg               <= '0';
                else
                    -- Logischer Rechtsshift im Daten- und Marker-Register.
                    shift_reg  <= '0' & shift_reg(WIDTH-1 downto 1);
                    new_marker := '0' & marker(WIDTH-1 downto 1);
                    marker     <= new_marker;
                    -- MSB liegt am Ausgang, sobald die '1' im Marker an
                    -- Position 0 angekommen ist. Danach Flag haengen lassen.
                    if new_marker(0) = '1' or last_bit_reg = '1' then
                        last_bit_reg <= '1';
                    end if;
                end if;
            end if;
        end if;
    end process SHIFT_PROC;
end architecture behavioral;

PISOShiftReg_tb.vhd
library ieee;
use ieee.std_logic_1164.all;

entity PISOShiftReg_tb is
end PISOShiftReg_tb;

architecture testbench of PISOShiftReg_tb is
    constant test_width : integer := 4; --STUDENT: SET TO ARBITRARY VALUE THAT FITS YOUR TESTDATA

    signal tb_in       : std_logic_vector(test_width-1 downto 0) := (others => '0');
    signal tb_out      : std_logic;
    signal tb_load     : std_logic := '0';
    signal tb_last_bit : std_logic;

    signal clk : std_logic;
    signal ce  : std_logic;

    component PISOShiftReg
        generic (
            WIDTH : integer
        );
        port (
            CLK      : in std_logic;
            CLK_EN   : in std_logic;
            LOAD     : in std_logic;
            D_IN     : in std_logic_vector(WIDTH-1 downto 0);
            D_OUT    : out std_logic;
            LAST_BIT : out std_logic
        );
    end component;
begin
    --generate basic clock
    clk_gen : process
    begin
        clk <= '1';
        wait for 1 ns;
        clk <= '0';
        wait for 1 ns;
    end process clk_gen;

    --generate clock enable signal
    clk_en_gen : process
    begin
        ce <= '1';
        wait for 1 ns;
        ce <= '0';
        wait for 9 ns;
    end process clk_en_gen;

    uut : PISOShiftReg
    generic map (WIDTH => test_width)
    port map (
        CLK      => clk,
        CLK_EN   => ce,
        LOAD     => tb_load,
        D_IN     => tb_in,
        D_OUT    => tb_out,
        LAST_BIT => tb_last_bit
    );

    --STUDENT: INSERT TESTBENCH CODE HERE (SIGNAL ASSIGNMENTS ETC.)
    stimuli : process
    begin
        -- Defaultwerte, etwas Zeit zum Einschwingen
        tb_load <= '0';
        tb_in   <= (others => '0');
        wait for 15 ns;

        -- Testfall 1: Datum 0101 laden und vollstaendig herausschieben.
        --   Erwartet: D_OUT-Sequenz 1,0,1,0; LAST_BIT='1' beim MSB, bleibt sticky.
        tb_in   <= "0101";
        tb_load <= '1';
        wait for 10 ns;        -- ein CE-Puls -> Laden
        tb_load <= '0';
        wait for 50 ns;        -- mehrere Shifts + Idle-Zustand pruefen

        -- Testfall 2: gleiches Datum erneut laden -> LAST_BIT muss zurueck auf '0'.
        tb_in   <= "0101";
        tb_load <= '1';
        wait for 10 ns;
        tb_load <= '0';
        wait for 40 ns;

        -- Testfall 3: anderes Bitmuster (MSB = 1).
        --   Erwartet: D_OUT-Sequenz 0,0,1,1; LAST_BIT='1' wenn MSB ausgegeben.
        tb_in   <= "1100";
        tb_load <= '1';
        wait for 10 ns;
        tb_load <= '0';
        wait for 50 ns;

        -- Testfall 4: All-Ones (Grenzfall, jedes Bit '1').
        tb_in   <= "1111";
        tb_load <= '1';
        wait for 10 ns;
        tb_load <= '0';
        wait for 50 ns;

        -- Testfall 5: All-Zeros (Grenzfall, jedes Bit '0').
        tb_in   <= "0000";
        tb_load <= '1';
        wait for 10 ns;
        tb_load <= '0';
        wait for 50 ns;

        -- Testfall 6: LOAD ueber mehrere Takte hoch halten -> jeden Takt neu laden.
        --   D_IN wechselt zwischendurch, das jeweils letzte Datum muss gewinnen.
        tb_in   <= "1010";
        tb_load <= '1';
        wait for 10 ns;
        tb_in   <= "0110";    -- aendert sich noch waehrend LOAD='1'
        wait for 20 ns;       -- weitere CE-Pulse mit LOAD='1'
        tb_load <= '0';
        wait for 50 ns;

        -- Simulation beenden
        report "PISOShiftReg-Testbench beendet." severity note;
        wait;
    end process stimuli;
end testbench;

PISOShiftReg_tb.vcd
$date
   Sun May 31 18:03:09 2026
$end
$version
  2017.3
$end
$timescale
  1ps
$end
$scope module PISOShiftReg_tb $end
$var wire 4 $ tb_in [3:0] $end
$var wire 1 % tb_out $end
$var wire 1 # tb_load $end
$var wire 1 & tb_last_bit $end
$var wire 1 ! clk $end
$var wire 1 " ce $end
$scope module uut $end
$var wire 1 ! CLK $end
$var wire 1 " CLK_EN $end
$var wire 1 # LOAD $end
$var wire 4 $ D_IN [3:0] $end
$var wire 1 % D_OUT $end
$var wire 1 & LAST_BIT $end
$var wire 4 ' shift_reg [3:0] $end
$var wire 4 ( marker [3:0] $end
$var wire 1 ) last_bit_reg $end
$scope task SHIFT_PROC $end
$upscope $end
$upscope $end
$upscope $end
$enddefinitions $end
#0
$dumpvars
1!
1"
0#
b0 $
0%
0&
b0 '
b0 (
0)
$end
#1000
0!
0"
#2000
1!
#3000
0!
#4000
1!
#5000
0!
#6000
1!
#7000
0!
#8000
1!
#9000
0!
#10000
1!
1"
#11000
0!
0"
#12000
1!
#13000
0!
#14000
1!
#15000
0!
1#
b101 $
#16000
1!
#17000
0!
#18000
1!
#19000
0!
#20000
1!
1"
1%
b101 '
b1000 (
#21000
0!
0"
#22000
1!
#23000
0!
#24000
1!
#25000
0!
0#
#26000
1!
#27000
0!
#28000
1!
#29000
0!
#30000
1!
1"
0%
b10 '
b100 (
#31000
0!
0"
#32000
1!
#33000
0!
#34000
1!
#35000
0!
#36000
1!
#37000
0!
#38000
1!
#39000
0!
#40000
1!
1"
1%
b1 '
b10 (
#41000
0!
0"
#42000
1!
#43000
0!
#44000
1!
#45000
0!
#46000
1!
#47000
0!
#48000
1!
#49000
0!
#50000
1!
1"
0%
1&
b0 '
b1 (
1)
#51000
0!
0"
#52000
1!
#53000
0!
#54000
1!
#55000
0!
#56000
1!
#57000
0!
#58000
1!
#59000
0!
#60000
1!
1"
b0 (
#61000
0!
0"
#62000
1!
#63000
0!
#64000
1!
#65000
0!
#66000
1!
#67000
0!
#68000
1!
#69000
0!
#70000
1!
1"
#71000
0!
0"
#72000
1!
#73000
0!
#74000
1!
#75000
0!
1#
#76000
1!
#77000
0!
#78000
1!
#79000
0!
#80000
1!
1"
1%
0&
b101 '
b1000 (
0)
#81000
0!
0"
#82000
1!
#83000
0!
#84000
1!
#85000
0!
0#
#86000
1!
#87000
0!
#88000
1!
#89000
0!
#90000
1!
1"
0%
b10 '
b100 (
#91000
0!
0"
#92000
1!
#93000
0!
#94000
1!
#95000
0!
#96000
1!
#97000
0!
#98000
1!
#99000
0!
#100000
1!
1"
1%
b1 '
b10 (
#101000
0!
0"
#102000
1!
#103000
0!
#104000
1!
#105000
0!
#106000
1!
#107000
0!
#108000
1!
#109000
0!
#110000
1!
1"
0%
1&
b0 '
b1 (
1)
#111000
0!
0"
#112000
1!
#113000
0!
#114000
1!
#115000
0!
#116000
1!
#117000
0!
#118000
1!
#119000
0!
#120000
1!
1"
b0 (
#121000
0!
0"
#122000
1!
#123000
0!
#124000
1!
#125000
0!
1#
b1100 $
#126000
1!
#127000
0!
#128000
1!
#129000
0!
#130000
1!
1"
0&
b1100 '
b1000 (
0)
#131000
0!
0"
#132000
1!
#133000
0!
#134000
1!
#135000
0!
0#
#136000
1!
#137000
0!
#138000
1!
#139000
0!
#140000
1!
1"
b110 '
b100 (
#141000
0!
0"
#142000
1!
#143000
0!
#144000
1!
#145000
0!
#146000
1!
#147000
0!
#148000
1!
#149000
0!
#150000
1!
1"
1%
b11 '
b10 (
#151000
0!
0"
#152000
1!
#153000
0!
#154000
1!
#155000
0!
#156000
1!
#157000
0!
#158000
1!
#159000
0!
#160000
1!
1"
1&
b1 '
b1 (
1)
#161000
0!
0"
#162000
1!
#163000
0!
#164000
1!
#165000
0!
#166000
1!
#167000
0!
#168000
1!
#169000
0!
#170000
1!
1"
0%
b0 '
b0 (
#171000
0!
0"
#172000
1!
#173000
0!
#174000
1!
#175000
0!
#176000
1!
#177000
0!
#178000
1!
#179000
0!
#180000
1!
1"
#181000
0!
0"
#182000
1!
#183000
0!
#184000
1!
#185000
0!
1#
b1111 $
#186000
1!
#187000
0!
#188000
1!
#189000
0!
#190000
1!
1"
1%
0&
b1111 '
b1000 (
0)
#191000
0!
0"
#192000
1!
#193000
0!
#194000
1!
#195000
0!
0#
#196000
1!
#197000
0!
#198000
1!
#199000
0!
#200000
1!
1"
b111 '
b100 (
#201000
0!
0"
#202000
1!
#203000
0!
#204000
1!
#205000
0!
#206000
1!
#207000
0!
#208000
1!
#209000
0!
#210000
1!
1"
b11 '
b10 (
#211000
0!
0"
#212000
1!
#213000
0!
#214000
1!
#215000
0!
#216000
1!
#217000
0!
#218000
1!
#219000
0!
#220000
1!
1"
1&
b1 '
b1 (
1)
#221000
0!
0"
#222000
1!
#223000
0!
#224000
1!
#225000
0!
#226000
1!
#227000
0!
#228000
1!
#229000
0!
#230000
1!
1"
0%
b0 '
b0 (
#231000
0!
0"
#232000
1!
#233000
0!
#234000
1!
#235000
0!
#236000
1!
#237000
0!
#238000
1!
#239000
0!
#240000
1!
1"
#241000
0!
0"
#242000
1!
#243000
0!
#244000
1!
#245000
0!
1#
b0 $
#246000
1!
#247000
0!
#248000
1!
#249000
0!
#250000
1!
1"
0&
b1000 (
0)
#251000
0!
0"
#252000
1!
#253000
0!
#254000
1!
#255000
0!
0#
#256000
1!
#257000
0!
#258000
1!
#259000
0!
#260000
1!
1"
b100 (
#261000
0!
0"
#262000
1!
#263000
0!
#264000
1!
#265000
0!
#266000
1!
#267000
0!
#268000
1!
#269000
0!
#270000
1!
1"
b10 (
#271000
0!
0"
#272000
1!
#273000
0!
#274000
1!
#275000
0!
#276000
1!
#277000
0!
#278000
1!
#279000
0!
#280000
1!
1"
1&
b1 (
1)
#281000
0!
0"
#282000
1!
#283000
0!
#284000
1!
#285000
0!
#286000
1!
#287000
0!
#288000
1!
#289000
0!
#290000
1!
1"
b0 (
#291000
0!
0"
#292000
1!
#293000
0!
#294000
1!
#295000
0!
#296000
1!
#297000
0!
#298000
1!
#299000
0!
#300000
1!
1"
#301000
0!
0"
#302000
1!
#303000
0!
#304000
1!
#305000
0!
1#
b1010 $
#306000
1!
#307000
0!
#308000
1!
#309000
0!
#310000
1!
1"
0&
b1010 '
b1000 (
0)
#311000
0!
0"
#312000
1!
#313000
0!
#314000
1!
#315000
0!
b110 $
#316000
1!
#317000
0!
#318000
1!
#319000
0!
#320000
1!
1"
b110 '
b1000 (
#321000
0!
0"
#322000
1!
#323000
0!
#324000
1!
#325000
0!
#326000
1!
#327000
0!
#328000
1!
#329000
0!
#330000
1!
1"
b1000 (
#331000
0!
0"
#332000
1!
#333000
0!
#334000
1!
#335000
0!
0#
#336000
1!
#337000
0!
#338000
1!
#339000
0!
#340000
1!
1"
1%
b11 '
b100 (
#341000
0!
0"
#342000
1!
#343000
0!
#344000
1!
#345000
0!
#346000
1!
#347000
0!
#348000
1!
#349000
0!
#350000
1!
1"
b1 '
b10 (
#351000
0!
0"
#352000
1!
#353000
0!
#354000
1!
#355000
0!
#356000
1!
#357000
0!
#358000
1!
#359000
0!
#360000
1!
1"
0%
1&
b0 '
b1 (
1)
#361000
0!
0"
#362000
1!
#363000
0!
#364000
1!
#365000
0!
#366000
1!
#367000
0!
#368000
1!
#369000
0!
#370000
1!
1"
b0 (
